{
  "_id": "ow-package_SuSEfirewall2_installed",
  "rule_id": "ow-package_SuSEfirewall2_installed",
  "scap_rule_id": "xccdf_org.ssgproject.content_rule_package_SuSEfirewall2_installed",
  "parent_rule_id": null,
  "metadata": {
    "name": "Install SuSEfirewall2 Package",
    "description": "{{{ describe_package_install(package=\"SuSEfirewall2\") }}}",
    "rationale": "The SuSEfirewall2 package should be installed to provide access control methods.",
    "source": {
      "upstream_id": "package_SuSEfirewall2_installed",
      "complianceascode_version": "0.1.73",
      "source_file": "converted_from_yaml",
      "cce_id": "CCE-83157-8",
      "imported_at": "2025-10-03T02:25:58.154252+00:00"
    }
  },
  "abstract": false,
  "severity": "medium",
  "category": "network_security",
  "security_function": "access_control",
  "tags": [
    "converted",
    "scap",
    "ssg",
    "severity_medium"
  ],
  "frameworks": {
    "nist": {
      "800-53r5": [
        "CM-7",
        "CA-3(5)",
        "AC-17(1)"
      ]
    },
    "stig": {
      "current": [
        "SRG-OS-000420-GPOS-00186",
        "SRG-OS-000096-GPOS-00050",
        "SLES-12-030030"
      ]
    }
  },
  "platform_implementations": {
    "rhel": {
      "versions": [
        "7",
        "8",
        "9"
      ],
      "check_method": "package",
      "check_command": "rpm -q SuSEfirewall2",
      "enable_command": "yum install -y SuSEfirewall2",
      "disable_command": "yum remove -y SuSEfirewall2",
      "service_dependencies": []
    },
    "ubuntu": {
      "versions": [
        "18.04",
        "20.04",
        "22.04",
        "24.04"
      ],
      "check_method": "package",
      "check_command": "dpkg -l | grep SuSEfirewall2",
      "enable_command": "apt-get install -y SuSEfirewall2",
      "disable_command": "apt-get remove -y SuSEfirewall2",
      "service_dependencies": []
    }
  },
  "platform_requirements": {
    "required_capabilities": [],
    "excluded_environments": []
  },
  "check_type": "template",
  "check_content": {
    "scap_rule_id": "xccdf_org.ssgproject.content_rule_package_SuSEfirewall2_installed",
    "method": "xccdf_evaluation",
    "expected_result": "pass"
  },
  "fix_available": true,
  "fix_content": {},
  "manual_remediation": "{{{ describe_package_install(package=\"SuSEfirewall2\") }}}",
  "remediation_complexity": "medium",
  "remediation_risk": "low",
  "dependencies": {
    "requires": [],
    "conflicts": [],
    "related": []
  },
  "source_file": "linux_os/guide/system/network/network-susefirewall2/package_SuSEfirewall2_installed/rule.yml",
  "source_hash": "sha256:5d4e105d6244e480",
  "version": "2024.2",
  "imported_at": "2025-10-03T02:25:58.154348+00:00",
  "updated_at": "2025-10-03T02:25:58.154350+00:00",
  "identifiers": {
    "cce": "CCE-83157-8"
  }
}