{
  "_id": "ow-package_pcsc_lite_ccid_installed",
  "rule_id": "ow-package_pcsc_lite_ccid_installed",
  "scap_rule_id": "xccdf_org.ssgproject.content_rule_package_pcsc_lite_ccid_installed",
  "parent_rule_id": null,
  "metadata": {
    "name": "Install the pcsc-lite-ccid package",
    "description": "{{{ describe_package_install(package=\"pcsc-lite-ccid\") }}}",
    "rationale": "The pcsc-lite-ccid package must be installed if it is to be available for\nmultifactor authentication using smartcards.",
    "source": {
      "upstream_id": "package_pcsc_lite_ccid_installed",
      "complianceascode_version": "0.1.73",
      "source_file": "converted_from_yaml",
      "cce_id": "CCE-86243-3",
      "imported_at": "2025-10-03T02:25:58.751613+00:00"
    }
  },
  "abstract": false,
  "severity": "medium",
  "category": "authentication",
  "security_function": "access_control",
  "tags": [
    "converted",
    "scap",
    "ssg",
    "severity_medium"
  ],
  "frameworks": {
    "nist": {
      "800-53r5": [
        "CM-6(a)"
      ]
    },
    "stig": {
      "current": [
        "SRG-OS-000375-GPOS-00160"
      ]
    }
  },
  "platform_implementations": {
    "rhel": {
      "versions": [
        "7",
        "8",
        "9"
      ],
      "check_method": "package",
      "check_command": "rpm -q pcsc-lite-ccid",
      "enable_command": "yum install -y pcsc-lite-ccid",
      "disable_command": "yum remove -y pcsc-lite-ccid",
      "service_dependencies": []
    },
    "ubuntu": {
      "versions": [
        "18.04",
        "20.04",
        "22.04",
        "24.04"
      ],
      "check_method": "package",
      "check_command": "dpkg -l | grep pcsc-lite-ccid",
      "enable_command": "apt-get install -y pcsc-lite-ccid",
      "disable_command": "apt-get remove -y pcsc-lite-ccid",
      "service_dependencies": []
    }
  },
  "platform_requirements": {
    "required_capabilities": [],
    "excluded_environments": []
  },
  "check_type": "template",
  "check_content": {
    "scap_rule_id": "xccdf_org.ssgproject.content_rule_package_pcsc_lite_ccid_installed",
    "method": "xccdf_evaluation",
    "expected_result": "pass"
  },
  "fix_available": true,
  "fix_content": {},
  "manual_remediation": "{{{ describe_package_install(package=\"pcsc-lite-ccid\") }}}",
  "remediation_complexity": "medium",
  "remediation_risk": "low",
  "dependencies": {
    "requires": [],
    "conflicts": [],
    "related": []
  },
  "source_file": "linux_os/guide/system/accounts/accounts-physical/screen_locking/smart_card_login/package_pcsc-lite-ccid_installed/rule.yml",
  "source_hash": "sha256:65e466cbc296b366",
  "version": "2024.2",
  "imported_at": "2025-10-03T02:25:58.751747+00:00",
  "updated_at": "2025-10-03T02:25:58.751750+00:00",
  "identifiers": {
    "cce": "CCE-86243-3"
  }
}