{
  "_id": "ow-package_postfix_installed",
  "rule_id": "ow-package_postfix_installed",
  "scap_rule_id": "xccdf_org.ssgproject.content_rule_package_postfix_installed",
  "parent_rule_id": null,
  "metadata": {
    "name": "The Postfix package is installed",
    "description": "A mail server is required for sending emails.\n{{{ describe_package_install(package=\"postfix\") }}}",
    "rationale": "Emails can be used to notify designated personnel about important\nsystem events such as failures or warnings.",
    "source": {
      "upstream_id": "package_postfix_installed",
      "complianceascode_version": "0.1.73",
      "source_file": "converted_from_yaml",
      "cce_id": "CCE-85983-5",
      "imported_at": "2025-10-03T02:25:57.267681+00:00"
    }
  },
  "abstract": false,
  "severity": "medium",
  "category": "system_hardening",
  "security_function": "access_control",
  "tags": [
    "converted",
    "scap",
    "ssg",
    "severity_medium"
  ],
  "frameworks": {
    "stig": {
      "current": [
        "SRG-OS-000046-GPOS-00022"
      ]
    }
  },
  "platform_implementations": {
    "rhel": {
      "versions": [
        "7",
        "8",
        "9"
      ],
      "check_method": "package",
      "check_command": "rpm -q postfix",
      "enable_command": "yum install -y postfix",
      "disable_command": "yum remove -y postfix",
      "service_dependencies": []
    },
    "ubuntu": {
      "versions": [
        "18.04",
        "20.04",
        "22.04",
        "24.04"
      ],
      "check_method": "package",
      "check_command": "dpkg -l | grep postfix",
      "enable_command": "apt-get install -y postfix",
      "disable_command": "apt-get remove -y postfix",
      "service_dependencies": []
    }
  },
  "platform_requirements": {
    "required_capabilities": [],
    "excluded_environments": []
  },
  "check_type": "template",
  "check_content": {
    "scap_rule_id": "xccdf_org.ssgproject.content_rule_package_postfix_installed",
    "method": "xccdf_evaluation",
    "expected_result": "pass"
  },
  "fix_available": true,
  "fix_content": {},
  "manual_remediation": "A mail server is required for sending emails.\n{{{ describe_package_install(package=\"postfix\") }}}",
  "remediation_complexity": "medium",
  "remediation_risk": "low",
  "dependencies": {
    "requires": [],
    "conflicts": [],
    "related": []
  },
  "source_file": "linux_os/guide/services/mail/package_postfix_installed/rule.yml",
  "source_hash": "sha256:b47c6e2c27a25588",
  "version": "2024.2",
  "imported_at": "2025-10-03T02:25:57.267771+00:00",
  "updated_at": "2025-10-03T02:25:57.267774+00:00",
  "identifiers": {
    "cce": "CCE-85983-5"
  }
}